{
  "target": [
    {
      "goldLevel": 1,
      "distanceIncome": 0.6,
      "killEnemyIncome": 1,
      "price": 50
    },
    {
      "goldLevel": 2,
      "distanceIncome": 0.8,
      "killEnemyIncome": 2,
      "price": 178
    },
    {
      "goldLevel": 3,
      "distanceIncome": 0.9,
      "killEnemyIncome": 3,
      "price": 306
    },
    {
      "goldLevel": 4,
      "distanceIncome": 1,
      "killEnemyIncome": 4,
      "price": 434
    },
    {
      "goldLevel": 5,
      "distanceIncome": 1.2,
      "killEnemyIncome": 5,
      "price": 562
    },
    {
      "goldLevel": 6,
      "distanceIncome": 1.4,
      "killEnemyIncome": 5.5,
      "price": 690
    },
    {
      "goldLevel": 7,
      "distanceIncome": 1.6,
      "killEnemyIncome": 5.5,
      "price": 818
    },
    {
      "goldLevel": 8,
      "distanceIncome": 1.8,
      "killEnemyIncome": 5.5,
      "price": 946
    },
    {
      "goldLevel": 9,
      "distanceIncome": 2,
      "killEnemyIncome": 5.5,
      "price": 1074
    },
    {
      "goldLevel": 10,
      "distanceIncome": 2.2,
      "killEnemyIncome": 5.5,
      "price": 1202
    },
    {
      "goldLevel": 11,
      "distanceIncome": 2.4,
      "killEnemyIncome": 6,
      "price": 1330
    },
    {
      "goldLevel": 12,
      "distanceIncome": 2.6,
      "killEnemyIncome": 6,
      "price": 1458
    },
    {
      "goldLevel": 13,
      "distanceIncome": 2.8,
      "killEnemyIncome": 6,
      "price": 1586
    },
    {
      "goldLevel": 14,
      "distanceIncome": 3,
      "killEnemyIncome": 6,
      "price": 1714
    },
    {
      "goldLevel": 15,
      "distanceIncome": 3.1,
      "killEnemyIncome": 6,
      "price": 1842
    },
    {
      "goldLevel": 16,
      "distanceIncome": 3.2,
      "killEnemyIncome": 6,
      "price": 1970
    },
    {
      "goldLevel": 17,
      "distanceIncome": 3.3,
      "killEnemyIncome": 6,
      "price": 2098
    },
    {
      "goldLevel": 18,
      "distanceIncome": 3.4,
      "killEnemyIncome": 6,
      "price": 2226
    },
    {
      "goldLevel": 19,
      "distanceIncome": 3.5,
      "killEnemyIncome": 6,
      "price": 2354
    },
    {
      "goldLevel": 20,
      "distanceIncome": 3.6,
      "killEnemyIncome": 6.3,
      "price": 2482
    },
    {
      "goldLevel": 21,
      "distanceIncome": 3.7,
      "killEnemyIncome": 6.3,
      "price": 2610
    },
    {
      "goldLevel": 22,
      "distanceIncome": 3.8,
      "killEnemyIncome": 6.3,
      "price": 2738
    },
    {
      "goldLevel": 23,
      "distanceIncome": 3.9,
      "killEnemyIncome": 6.3,
      "price": 2866
    },
    {
      "goldLevel": 24,
      "distanceIncome": 4,
      "killEnemyIncome": 6.3,
      "price": 2994
    },
    {
      "goldLevel": 25,
      "distanceIncome": 4.1,
      "killEnemyIncome": 6.3,
      "price": 3122
    },
    {
      "goldLevel": 26,
      "distanceIncome": 4.2,
      "killEnemyIncome": 6.3,
      "price": 3250
    },
    {
      "goldLevel": 27,
      "distanceIncome": 4.3,
      "killEnemyIncome": 6.3,
      "price": 3378
    },
    {
      "goldLevel": 28,
      "distanceIncome": 4.4,
      "killEnemyIncome": 6.3,
      "price": 3506
    },
    {
      "goldLevel": 29,
      "distanceIncome": 4.5,
      "killEnemyIncome": 6.3,
      "price": 3634
    },
    {
      "goldLevel": 30,
      "distanceIncome": 4.6,
      "killEnemyIncome": 6.3,
      "price": 3762
    },
    {
      "goldLevel": 31,
      "distanceIncome": 4.7,
      "killEnemyIncome": 6.5,
      "price": 3890
    },
    {
      "goldLevel": 32,
      "distanceIncome": 4.8,
      "killEnemyIncome": 6.5,
      "price": 4018
    },
    {
      "goldLevel": 33,
      "distanceIncome": 4.9,
      "killEnemyIncome": 6.5,
      "price": 4146
    },
    {
      "goldLevel": 34,
      "distanceIncome": 5,
      "killEnemyIncome": 6.5,
      "price": 4274
    },
    {
      "goldLevel": 35,
      "distanceIncome": 5.1,
      "killEnemyIncome": 6.5,
      "price": 4402
    },
    {
      "goldLevel": 36,
      "distanceIncome": 5.2,
      "killEnemyIncome": 6.5,
      "price": 4530
    },
    {
      "goldLevel": 37,
      "distanceIncome": 5.3,
      "killEnemyIncome": 6.5,
      "price": 4658
    },
    {
      "goldLevel": 38,
      "distanceIncome": 5.4,
      "killEnemyIncome": 6.5,
      "price": 4786
    },
    {
      "goldLevel": 39,
      "distanceIncome": 5.49999999999999,
      "killEnemyIncome": 6.5,
      "price": 4914
    },
    {
      "goldLevel": 40,
      "distanceIncome": 5.59999999999999,
      "killEnemyIncome": 6.5,
      "price": 5042
    },
    {
      "goldLevel": 41,
      "distanceIncome": 5.69999999999999,
      "killEnemyIncome": 6.5,
      "price": 5170
    },
    {
      "goldLevel": 42,
      "distanceIncome": 5.79999999999999,
      "killEnemyIncome": 6.5,
      "price": 5298
    },
    {
      "goldLevel": 43,
      "distanceIncome": 5.89999999999999,
      "killEnemyIncome": 6.5,
      "price": 5426
    },
    {
      "goldLevel": 44,
      "distanceIncome": 5.99999999999999,
      "killEnemyIncome": 6.5,
      "price": 5554
    },
    {
      "goldLevel": 45,
      "distanceIncome": 6.09999999999999,
      "killEnemyIncome": 6.5,
      "price": 5682
    },
    {
      "goldLevel": 46,
      "distanceIncome": 6.19999999999999,
      "killEnemyIncome": 6.5,
      "price": 5810
    },
    {
      "goldLevel": 47,
      "distanceIncome": 6.29999999999999,
      "killEnemyIncome": 6.5,
      "price": 5938
    },
    {
      "goldLevel": 48,
      "distanceIncome": 6.39999999999999,
      "killEnemyIncome": 6.5,
      "price": 6066
    },
    {
      "goldLevel": 49,
      "distanceIncome": 6.49999999999999,
      "killEnemyIncome": 6.5,
      "price": 6194
    },
    {
      "goldLevel": 50,
      "distanceIncome": 6.59999999999999,
      "killEnemyIncome": 6.5,
      "price": 6322
    }
  ]
}